currentscape/__init__.py
currentscape/config_parser.py
currentscape/currents.py
currentscape/currentscape.py
currentscape/data_processing.py
currentscape/datasets.py
currentscape/ions.py
currentscape/legends.py
currentscape/mapper.py
currentscape/plotting.py
currentscape/voltages.py
doc/Makefile
doc/source/api.rst
doc/source/changelog.rst
doc/source/conf.py
doc/source/index.rst
doc/source/tutorial.rst
doc/source/images/plot.png
doc/source/images/quickstart_plot.png
examples/original_paper_plot/LICENSE.txt
examples/original_paper_plot/LICENSE_CC0-1.0
examples/original_paper_plot/__init__.py
examples/original_paper_plot/config.json
examples/original_paper_plot/get_currents.py
examples/original_paper_plot/integrate_single_compartment_and_plot_currentscape.py
examples/original_paper_plot/single_compartment.py
examples/original_paper_plot/parameters-and-initial-conditions/initial-conditions.txt
examples/original_paper_plot/parameters-and-initial-conditions/model-A-name-HZFTSB.txt
examples/original_paper_plot/parameters-and-initial-conditions/model-B-name-8XCUQE.txt
examples/original_paper_plot/parameters-and-initial-conditions/model-C-name-C1L1R0.txt
examples/original_paper_plot/parameters-and-initial-conditions/model-D-name-KI47XV.txt
examples/original_paper_plot/parameters-and-initial-conditions/model-E-name-OG1RE2.txt
examples/original_paper_plot/parameters-and-initial-conditions/model-F-name-B7S21N.txt
examples/original_paper_plot/parameters-and-initial-conditions/model-FIG2-name-1BLGMA.txt
examples/original_paper_plot/parameters-and-initial-conditions/model-FIG3-name-VVECT5.txt
examples/use_case/LICENSE.txt
examples/use_case/LICENSE_CC-BY-CA-SA-4.0
examples/use_case/__init__.py
examples/use_case/plot.py
examples/use_case/run.py
examples/use_case/run_py.sh
examples/use_case/config/params/final.json
examples/use_case/config/params/pyr.json
examples/use_case/mechanisms/CaDynamics_DC0.mod
examples/use_case/mechanisms/Ca_HVA2.mod
currentscape-1.0.20.dist-info/AUTHORS.rst
currentscape-1.0.20.dist-info/COPYING
currentscape-1.0.20.dist-info/LICENSE.txt
currentscape-1.0.20.dist-info/METADATA
currentscape-1.0.20.dist-info/WHEEL
currentscape-1.0.20.dist-info/top_level.txt
currentscape-1.0.20.dist-info/RECORD
