Metadata-Version: 2.2
Name: currentscape
Version: 1.0.20
Summary: Module to easily plot currentscape.
Author: Blue Brain Project, EPFL
License: Currentscape is licensed under the Apache License, unless noted otherwise, e.g., for external 
Project-URL: Homepage, https://github.com/openbraininstitute/Currentscape
Project-URL: Source, https://github.com/openbraininstitute/Currentscape
Project-URL: Repository, https://github.com/openbraininstitute/Currentscape.git
Project-URL: Tracker, https://github.com/openbraininstitute/Currentscape/issues
Project-URL: Documentation, https://currentscape.readthedocs.io/en/latest
Classifier: Development Status :: 5 - Production/Stable
Classifier: Intended Audience :: Education
Classifier: Intended Audience :: Science/Research
Classifier: Programming Language :: Python
Classifier: Programming Language :: Python :: 3
Classifier: Programming Language :: Python :: 3.9
Classifier: Programming Language :: Python :: 3.10
Classifier: Programming Language :: Python :: 3.11
Classifier: Programming Language :: Python :: 3.12
Classifier: Topic :: Scientific/Engineering :: Bio-Informatics
Requires-Python: >=3.8
License-File: LICENSE.txt
License-File: COPYING
License-File: AUTHORS.rst
Requires-Dist: numpy
Requires-Dist: matplotlib
Requires-Dist: palettable
Provides-Extra: docs
Requires-Dist: sphinx; extra == "docs"
Requires-Dist: sphinx-bluebrain-theme; extra == "docs"
Provides-Extra: example
Requires-Dist: scipy; extra == "example"
Requires-Dist: bluepyopt; extra == "example"
Requires-Dist: emodelrunner>=1.2.5; extra == "example"
